README.rst
setup.py
pydatalogger/__init__.py
pydatalogger/acquisition.py
pydatalogger/commands.py
pydatalogger/core.py
pydatalogger/devices.py
pydatalogger/sensors.py
pydatalogger/telemetry.py
pydatalogger/util.py
pydatalogger.egg-info/PKG-INFO
pydatalogger.egg-info/SOURCES.txt
pydatalogger.egg-info/dependency_links.txt
pydatalogger.egg-info/entry_points.txt
pydatalogger.egg-info/not-zip-safe
pydatalogger.egg-info/requires.txt
pydatalogger.egg-info/top_level.txt
pydatalogger/target/__init__.py
pydatalogger/target/mqtt.py
pydatalogger/target/stream.py